restconf_cli.py
tests/__init__.py
tests/test_restconf_cli.py
restconf_cli-0.1.5.dist-info/LICENSE
restconf_cli-0.1.5.dist-info/METADATA
restconf_cli-0.1.5.dist-info/WHEEL
restconf_cli-0.1.5.dist-info/entry_points.txt
restconf_cli-0.1.5.dist-info/top_level.txt
restconf_cli-0.1.5.dist-info/RECORD
