Metadata-Version: 2.1
Name: restconf-cli
Version: 0.1.5
Summary: command line tool for restconf
Home-page: https://github.com/muhammad-rafi/restconf-cli
Author: Muhammad Rafi
Author-email: murafi@cisco.com
License: MIT
Classifier: Development Status :: 5 - Production/Stable
Classifier: Environment :: Console
Classifier: Intended Audience :: Developers
Classifier: Intended Audience :: End Users/Desktop
Classifier: Intended Audience :: System Administrators
Classifier: Operating System :: OS Independent
Classifier: License :: OSI Approved :: MIT License
Classifier: Programming Language :: Python :: 3.8
Classifier: Programming Language :: Python :: 3.9
Classifier: Programming Language :: Python :: 3.10
Classifier: Topic :: Other/Nonlisted Topic
Requires-Python: >=3.8
License-File: LICENSE
Requires-Dist: click (==7.1.2)
Requires-Dist: requests (==2.26.0)
Requires-Dist: rich (==11.2.0)
